flask_toastr.py
Flask_Toastr-0.5.8.dist-info/LICENSE
Flask_Toastr-0.5.8.dist-info/METADATA
Flask_Toastr-0.5.8.dist-info/WHEEL
Flask_Toastr-0.5.8.dist-info/top_level.txt
Flask_Toastr-0.5.8.dist-info/RECORD
