Metadata-Version: 2.1
Name: Flask-Toastr
Version: 0.5.8
Summary: Showing non-blocking notifications in Flask templates using toastr.
Home-page: https://github.com/wiltonsr/Flask-Toastr/
Author: Wilton Rodrigues
Author-email: wiltonsr94@gmail.com
License: MIT
Platform: any
Classifier: Environment :: Web Environment
Classifier: Intended Audience :: Developers
Classifier: License :: OSI Approved :: MIT License
Classifier: Operating System :: OS Independent
Classifier: Programming Language :: Python
Classifier: Topic :: Internet :: WWW/HTTP :: Dynamic Content
Classifier: Topic :: Software Development :: Libraries :: Python Modules
License-File: LICENSE
